{
    "patterns": [
    {
        "name": "dragon",
        "length": 5,
        "angle": 90,
        "axiom": "FX",
        "iterations": 12,
        "rule1": "X=X+YF",
        "rule2": "Y=FX-Y",
        "rule3": "",
        "rule4": "",
        "rule5": "",
        "auto": false,
        "posSelected": "",
        "posMouse": [233, 178]
    }, {
        "name": "pentagon",
        "length": 100,
        "angle": 72,
        "axiom": "F-F-F-F-F",
        "iterations": 4,
        "rule1": "F=F-F++F+F-F-F",
        "rule2": "",
        "rule3": "",
        "rule4": "",
        "rule5": "",
        "auto": true,
        "posSelected": "",
        "posMouse": [52, 321]
    }, {
        "name": "octal",
        "length": 8,
        "angle": 45,
        "axiom": "L--F--L--F",
        "iterations": 10,
        "rule1": "L=+R-F-R+",
        "rule2": "R=-L+F+L-",
        "rule3": "",
        "rule4": "",
        "rule5": "",
        "auto": false,
        "posSelected": "bottom-center",
        "posMouse": [0, 0]
    }, {
        "name": "hexAngle",
        "length": 500,
        "angle": 60,
        "axiom": "YF",
        "iterations": 7,
        "rule1": "X=YF+XF+Y",
        "rule2": "Y=XF-YF-X",
        "rule3": "",
        "rule4": "",
        "rule5": "",
        "auto": true,
        "posSelected": "",
        "posMouse": [503, 548]
    }, {
        "name": "cross",
        "length": 200,
        "angle": 90,
        "axiom": "F+F+F+F",
        "iterations": 5,
        "rule1": "F=F+FF++F+F",
        "rule2": "",
        "rule3": "",
        "rule4": "",
        "rule5": "",
        "auto": true,
        "posSelected": "",
        "posMouse": [293, 54]
    }, {
        "name": "rings",
        "length": 50,
        "angle": 90,
        "axiom": "F+F+F+F",
        "iterations": 4,
        "rule1": "F=FF+F+F+F+F+F-F",
        "rule2": "",
        "rule3": "",
        "rule4": "",
        "rule5": "",
        "auto": true,
        "posSelected": "",
        "posMouse": [105, 196]
    }, {
        "name": "hexGosper",
        "length": 100,
        "angle": 60,
        "axiom": "XF",
        "iterations": 5,
        "rule1": "X=X+YF++YF-FX--FXFX-YF+",
        "rule2": "Y=-FX+YFYF++YF+FX--FX-Y",
        "rule3": "",
        "rule4": "",
        "rule5": "",
        "auto": true,
        "posSelected": "",
        "posMouse": [116, 160]
    }, {
        "name": "board",
        "length": 118,
        "angle": 90,
        "axiom": "F+F+F+F",
        "iterations": 4,
        "rule1": "F=FF+F+F+F+FF",
        "rule2": "",
        "rule3": "",
        "rule4": "",
        "rule5": "",
        "auto": true,
        "posSelected": "bottom-left",
        "posMouse": [0, 0]
    }, {
        "name": "triAwesome",
        "length": 15,
        "angle": 120,
        "axiom": "F+F+F",
        "iterations": 6,
        "rule1": "F=F-F+F",
        "rule2": "",
        "rule3": "",
        "rule4": "",
        "rule5": "",
        "auto": false,
        "posSelected": "",
        "posMouse": [422, 120]
    }, {
        "name": "rice",
        "length": 300,
        "angle": 26,
        "axiom": "Y",
        "iterations": 6,
        "rule1": "X=X[-FFF][+FFF]FX",
        "rule2": "Y=YFX[+Y][-Y]",
        "rule3": "",
        "rule4": "",
        "rule5": "",
        "auto": true,
        "posSelected": "bottom-center",
        "posMouse": [0, 0]
    }, {
        "name": "simpleTree4",
        "length": 300,
        "angle": 30,
        "axiom": "F",
        "iterations": 6,
        "rule1": "F=F[+F]F[-F][F]",
        "rule2": "",
        "rule3": "",
        "rule4": "",
        "rule5": "",
        "auto": true,
        "posSelected": "bottom-center",
        "posMouse": [0, 0]
    }, {
        "name": "simpleTree5",
        "length": 300,
        "angle": 25.7,
        "axiom": "X",
        "iterations": 7,
        "rule1": "F=FF",
        "rule2": "X=F[+X][-X]FX",
        "rule3": "",
        "rule4": "",
        "rule5": "",
        "auto": true,
        "posSelected": "bottom-center",
        "posMouse": [0, 0]
    }, {
        "name": "simpleTree1",
        "length": 150,
        "angle": 30,
        "axiom": "X",
        "iterations": 7,
        "rule1": "F=FF",
        "rule2": "X=F[--X][++X]F[+X][-X]FFX",
        "rule3": "",
        "rule4": "",
        "rule5": "",
        "auto": true,
        "posSelected": "bottom-center",
        "posMouse": [0, 0]
    }, {
        "name": "simpleTree2",
        "length": 150,
        "angle": 30,
        "axiom": "X",
        "iterations": 7,
        "rule1": "F=FF",
        "rule2": "X=F[-F-X][+X]FF[-X][+F+X]+FX",
        "rule3": "",
        "rule4": "",
        "rule5": "",
        "auto": true,
        "posSelected": "bottom-center",
        "posMouse": [0, 0]
    }, {
        "name": "simpleTree3",
        "length": 150,
        "angle": 30,
        "axiom": "X",
        "iterations": 7,
        "rule1": "F=FF",
        "rule2": "X=F[-FX][+X]-F+F[-X][+F+X]+FX",
        "rule3": "",
        "rule4": "",
        "rule5": "",
        "auto": true,
        "posSelected": "bottom-center",
        "posMouse": [0, 0]
    }]

}